LICENSE
MANIFEST.in
README.md
doc.md
setup.py
promela/__init__.py
promela/_version.py
promela/ast.py
promela/lex.py
promela/promela_parsetab.py
promela/yacc.py
promela.egg-info/PKG-INFO
promela.egg-info/SOURCES.txt
promela.egg-info/dependency_links.txt
promela.egg-info/requires.txt
promela.egg-info/top_level.txt
tests/yacc_test.py