Metadata-Version: 1.1
Name: promela
Version: 0.0.2
Summary: Parser and abstract syntax tree for the Promela modeling language.
Home-page: https://github.com/johnyf/promela
Author: Ioannis Filippidis
Author-email: jfilippidis@gmail.com
License: BSD
Keywords: promela,parser,syntax tree,ply,lex,yacc
Platform: UNKNOWN
Classifier: Development Status :: 2 - Pre-Alpha
Classifier: Intended Audience :: Science/Research
Classifier: License :: OSI Approved :: BSD License
Classifier: Operating System :: OS Independent
Classifier: Programming Language :: Python
Classifier: Programming Language :: Python :: 2.7
Classifier: Programming Language :: Python :: 3
Classifier: Topic :: Scientific/Engineering
